{
    "version": "0.9.0",
    "architecture": {
        "64bit": {
            "url": "https://github.com/skyhook-io/radar/releases/download/v0.9.0/radar_v0.9.0_windows_amd64.zip",
            "bin": [
                "kubectl-radar.exe"
            ],
            "hash": "6ca3593d9a71003fc7b09073cb508d1ff3def25fef8c82f022889fd1d5ac20fb"
        }
    },
    "homepage": "https://github.com/skyhook-io/radar",
    "license": "Apache-2.0",
    "description": "Modern Kubernetes visibility — topology, traffic, and Helm management",
    "post_install": [
        "Write-Host 'Run: kubectl-radar or radar' -ForegroundColor Green"
    ]
}
