{
    "version": "1.2.1",
    "architecture": {
        "64bit": {
            "url": "https://github.com/skyhook-io/radar/releases/download/v1.2.1/radar-desktop_v1.2.1_windows_amd64.zip",
            "bin": [
                "Radar.exe"
            ],
            "shortcuts": [
                ["Radar.exe", "Radar"]
            ],
            "hash": "faacdb13ea89ba3e5cc1ce70dd4afbeb54ee59970707400cf036c260ebfce65c"
        }
    },
    "homepage": "https://github.com/skyhook-io/radar",
    "license": "Apache-2.0",
    "description": "Radar Desktop — Kubernetes visibility with topology, traffic, and Helm management",
    "post_install": [
        "Write-Host 'Radar Desktop installed. Launch from Start Menu or run: radar-desktop' -ForegroundColor Green"
    ]
}
